cht_hurrywave/__init__.py
cht_hurrywave/bathymetry.py
cht_hurrywave/boundary_conditions.py
cht_hurrywave/grid.py
cht_hurrywave/hurrywave.py
cht_hurrywave/hurrywave_builder.py
cht_hurrywave/input.py
cht_hurrywave/mask.py
cht_hurrywave/observation_points.py
cht_hurrywave/to_xugrid.py
cht_hurrywave/waveblocking.py
cht_hurrywave-1.0.1.dist-info/LICENSE
cht_hurrywave-1.0.1.dist-info/METADATA
cht_hurrywave-1.0.1.dist-info/WHEEL
cht_hurrywave-1.0.1.dist-info/top_level.txt
cht_hurrywave-1.0.1.dist-info/RECORD
