Metadata-Version: 2.1
Name: cht_hurrywave
Version: 1.0.1
Author-email: Maarten van Ormondt <maarten.vanormondt@deltares-usa.us>, Koen van Asselt <koen.vanassely@deltares.nl>
Requires-Python: >=3.10
License-File: LICENSE
Requires-Dist: geopandas
Requires-Dist: numpy
Requires-Dist: pandas
Requires-Dist: pyproj
Requires-Dist: shapely
Requires-Dist: scipy
Requires-Dist: xarray
Requires-Dist: matplotlib
Requires-Dist: pyyaml
Requires-Dist: xugrid
Requires-Dist: toml
Requires-Dist: affine
Requires-Dist: datashader
Requires-Dist: cht-utils
